<annotation>
	<folder>116-125</folder>
	<filename>118.jpg</filename>
	<path>C:\Users\Mr. Fasial\Desktop\116-125\118.jpg</path>
	<source>
		<database>Unknown</database>
	</source>
	<size>
		<width>256</width>
		<height>256</height>
		<depth>3</depth>
	</size>
	<segmented>0</segmented>
	<object>
		<name>GroundNut_Leaf</name>
		<pose>Unspecified</pose>
		<truncated>0</truncated>
		<difficult>0</difficult>
		<bndbox>
			<xmin>132</xmin>
			<ymin>118</ymin>
			<xmax>191</xmax>
			<ymax>144</ymax>
		</bndbox>
	</object>
	<object>
		<name>GroundNut_Leaf</name>
		<pose>Unspecified</pose>
		<truncated>0</truncated>
		<difficult>0</difficult>
		<bndbox>
			<xmin>131</xmin>
			<ymin>147</ymin>
			<xmax>176</xmax>
			<ymax>181</ymax>
		</bndbox>
	</object>
	<object>
		<name>GroundNut_Leaf</name>
		<pose>Unspecified</pose>
		<truncated>0</truncated>
		<difficult>0</difficult>
		<bndbox>
			<xmin>102</xmin>
			<ymin>145</ymin>
			<xmax>128</xmax>
			<ymax>187</ymax>
		</bndbox>
	</object>
	<object>
		<name>GroundNut_Leaf</name>
		<pose>Unspecified</pose>
		<truncated>0</truncated>
		<difficult>0</difficult>
		<bndbox>
			<xmin>128</xmin>
			<ymin>49</ymin>
			<xmax>150</xmax>
			<ymax>76</ymax>
		</bndbox>
	</object>
	<object>
		<name>GroundNut_Leaf</name>
		<pose>Unspecified</pose>
		<truncated>0</truncated>
		<difficult>0</difficult>
		<bndbox>
			<xmin>95</xmin>
			<ymin>91</ymin>
			<xmax>124</xmax>
			<ymax>119</ymax>
		</bndbox>
	</object>
	<object>
		<name>GroundNut_Leaf</name>
		<pose>Unspecified</pose>
		<truncated>0</truncated>
		<difficult>0</difficult>
		<bndbox>
			<xmin>24</xmin>
			<ymin>42</ymin>
			<xmax>48</xmax>
			<ymax>73</ymax>
		</bndbox>
	</object>
	<object>
		<name>GroundNut_Leaf</name>
		<pose>Unspecified</pose>
		<truncated>0</truncated>
		<difficult>0</difficult>
		<bndbox>
			<xmin>76</xmin>
			<ymin>37</ymin>
			<xmax>106</xmax>
			<ymax>52</ymax>
		</bndbox>
	</object>
	<object>
		<name>GroundNut_Leaf</name>
		<pose>Unspecified</pose>
		<truncated>0</truncated>
		<difficult>0</difficult>
		<bndbox>
			<xmin>217</xmin>
			<ymin>2</ymin>
			<xmax>246</xmax>
			<ymax>23</ymax>
		</bndbox>
	</object>
</annotation>
